kpu/__init__.py
kpu/client/__init__.py
kpu/client/cluster.py
kpu/client/compute.py
kpu/client/context.py
kpu/client/decorator.py
kpu/client/event.py
kpu/client/grpc.py
kpu/client/init.py
kpu/client/metrics.py
kpu/client/aio/__init__.py
kpu/client/aio/api_client.py
kpu/client/aio/discovery.py
kpu/client/aio/dynamic.py
kpu/client/aio/resource.py
kpu/client/aio/rest.py
kpu/client/aio/stream.py
kpu/client/aio/watch.py
kpu/client/models/io_k8s_api_core_v1_affinity.py
kpu/client/models/io_k8s_api_core_v1_app_armor_profile.py
kpu/client/models/io_k8s_api_core_v1_attached_volume.py
kpu/client/models/io_k8s_api_core_v1_avoid_pods.py
kpu/client/models/io_k8s_api_core_v1_aws_elastic_block_store_volume_source.py
kpu/client/models/io_k8s_api_core_v1_azure_disk_volume_source.py
kpu/client/models/io_k8s_api_core_v1_azure_file_persistent_volume_source.py
kpu/client/models/io_k8s_api_core_v1_azure_file_volume_source.py
kpu/client/models/io_k8s_api_core_v1_binding.py
kpu/client/models/io_k8s_api_core_v1_capabilities.py
kpu/client/models/io_k8s_api_core_v1_ceph_fs_persistent_volume_source.py
kpu/client/models/io_k8s_api_core_v1_ceph_fs_volume_source.py
kpu/client/models/io_k8s_api_core_v1_cinder_persistent_volume_source.py
kpu/client/models/io_k8s_api_core_v1_cinder_volume_source.py
kpu/client/models/io_k8s_api_core_v1_client_ip_config.py
kpu/client/models/io_k8s_api_core_v1_cluster_trust_bundle_projection.py
kpu/client/models/io_k8s_api_core_v1_component_condition.py
kpu/client/models/io_k8s_api_core_v1_component_status.py
kpu/client/models/io_k8s_api_core_v1_component_status_list.py
kpu/client/models/io_k8s_api_core_v1_config_map.py
kpu/client/models/io_k8s_api_core_v1_config_map_env_source.py
kpu/client/models/io_k8s_api_core_v1_config_map_key_selector.py
kpu/client/models/io_k8s_api_core_v1_config_map_list.py
kpu/client/models/io_k8s_api_core_v1_config_map_node_config_source.py
kpu/client/models/io_k8s_api_core_v1_config_map_projection.py
skytorch-0.1.0.dev0.dist-info/licenses/LICENSE
skytorch-0.1.0.dev0.dist-info/METADATA
skytorch-0.1.0.dev0.dist-info/WHEEL
skytorch-0.1.0.dev0.dist-info/entry_points.txt
skytorch-0.1.0.dev0.dist-info/top_level.txt
skytorch-0.1.0.dev0.dist-info/RECORD
